pandarss/__init__.py
pandarss/alipay.py
pandarss/pandarss.py
pandarss/trapi.py
pandarss/utils.py
pandarss/views/account.html
pandarss/views/alipay_return.html
pandarss/views/error.html
pandarss/views/footer.html
pandarss/views/header.html
pandarss/views/index.html
pandarss/views/message.html
pandarss/views/nheader.html
pandarss/views/order_cform.html
pandarss/views/order_form.html
pandarss/views/orders.html
pandarss/views/password.html
pandarss/views/product.html
pandarss/views/css/bootstrap.min.css
pandarss/views/css/ie10-viewport-bug-workaround.js
pandarss/views/css/main.css
pandarss/views/js/bootstrap.min.js
pandarss/views/js/html5shiv.min.js
pandarss/views/js/ie-emulation-modes-warning.js
pandarss/views/js/jquery.min.js
pandarss/views/js/respond.min.js
pandarss-0.2.dist-info/DESCRIPTION.rst
pandarss-0.2.dist-info/eager_resources.txt
pandarss-0.2.dist-info/entry_points.txt
pandarss-0.2.dist-info/METADATA
pandarss-0.2.dist-info/metadata.json
pandarss-0.2.dist-info/RECORD
pandarss-0.2.dist-info/top_level.txt
pandarss-0.2.dist-info/WHEEL
pandarss-0.2.dist-info/zip-safe
