Metadata-Version: 2.0
Name: pandarss
Version: 0.2
Summary: ToughRADIUS Self-service Portal
Home-page: https://github.com/PandaPark/PandaRSS
Author: pandaman
Author-email: pandaman1999@foxmail.com
License: BSD
Keywords: radius,toughradius,self-service ,pandarss
Platform: UNKNOWN
Classifier: Development Status :: 6 - Mature
Classifier: Intended Audience :: Developers
Classifier: Programming Language :: Python :: 2.7
Classifier: Topic :: Software Development :: Libraries :: Python Modules
Classifier: Topic :: System :: Systems Administration :: Authentication/Directory
Requires-Dist: Twisted (>=15.0.0)
Requires-Dist: bottle (>=0.12.7)
